myev/__init__.py
myev/environment.py
myev/py.typed
myev/validators.py
myev-0.10.0.dist-info/LICENSE
myev-0.10.0.dist-info/METADATA
myev-0.10.0.dist-info/WHEEL
myev-0.10.0.dist-info/RECORD
