Metadata-Version: 2.1
Name: myev
Version: 0.10.0
Summary: Environment variables fetcher.
License: MIT
Author: Łukasz Wieczorek
Author-email: wieczorek1990@gmail.com
Requires-Python: >=3.11,<4.0
Classifier: License :: OSI Approved :: MIT License
Classifier: Programming Language :: Python :: 3
Classifier: Programming Language :: Python :: 3.11
Requires-Dist: validators (>=0.22.0,<0.23.0)
